llmutils/__init__.py
llmutils/index.py
llmutils/lock.py
llmutils/log.py
llmutils/oai.py
llmutils/retry.py
llmutils-0.1.6.dist-info/METADATA
llmutils-0.1.6.dist-info/WHEEL
llmutils-0.1.6.dist-info/top_level.txt
llmutils-0.1.6.dist-info/RECORD
